skmob/__init__.py
skmob/core/__init__.py
skmob/core/flowdataframe.py
skmob/core/trajectorydataframe.py
skmob/io/__init__.py
skmob/io/file.py
skmob/measures/__init__.py
skmob/measures/collective.py
skmob/measures/evaluation.py
skmob/measures/individual.py
skmob/models/__init__.py
skmob/models/epr.py
skmob/models/gravity.py
skmob/models/markov_diary_generator.py
skmob/models/radiation.py
skmob/preprocessing/__init__.py
skmob/preprocessing/clustering.py
skmob/preprocessing/compression.py
skmob/preprocessing/detection.py
skmob/preprocessing/filtering.py
skmob/preprocessing/routing.py
skmob/privacy/__init__.py
skmob/privacy/attacks.py
skmob/tessellation/__init__.py
skmob/tessellation/tilers.py
skmob/utils/__init__.py
skmob/utils/constants.py
skmob/utils/gislib.py
skmob/utils/plot.py
skmob/utils/utils.py
scikit_mobility_unofficial-1.0.dist-info/LICENSE
scikit_mobility_unofficial-1.0.dist-info/LICENSE.txt
scikit_mobility_unofficial-1.0.dist-info/METADATA
scikit_mobility_unofficial-1.0.dist-info/WHEEL
scikit_mobility_unofficial-1.0.dist-info/top_level.txt
scikit_mobility_unofficial-1.0.dist-info/RECORD
