Metadata-Version: 2.1
Name: scikit-mobility-unofficial
Version: 1.0
Summary: A toolbox for analyzing and processing mobility data.
Home-page: UNKNOWN
Maintainer: skmob Developers
Maintainer-email: gianni.barlacchi@gmail.com
License: MIT
Platform: UNKNOWN
Classifier: Intended Audience :: Science/Research
Classifier: Intended Audience :: Developers
Classifier: License :: OSI Approved
Classifier: Programming Language :: Python
Classifier: Topic :: Software Development
Classifier: Topic :: Scientific/Engineering
Classifier: Operating System :: Microsoft :: Windows
Classifier: Operating System :: Unix
Classifier: Operating System :: MacOS
Classifier: Programming Language :: Python :: 3.6
Classifier: Programming Language :: Python :: 3.7
Requires-Python: >=3.6
Requires-Dist: numpy
Requires-Dist: pandas
Requires-Dist: geopandas
Requires-Dist: scipy
Requires-Dist: powerlaw
Requires-Dist: tqdm
Requires-Dist: requests
Requires-Dist: scikit-learn
Requires-Dist: statsmodels
Requires-Dist: folium
Requires-Dist: matplotlib
Requires-Dist: geojson
Requires-Dist: shapely
Requires-Dist: fiona
